graphlayer/__init__.py
graphlayer/connections.py
graphlayer/core.py
graphlayer/iterables.py
graphlayer/memo.py
graphlayer/representations.py
graphlayer/resolvers.py
graphlayer/schema.py
graphlayer/sqlalchemy.py
graphlayer/unions.py
graphlayer/graphql/__init__.py
graphlayer/graphql/naming.py
graphlayer/graphql/parser.py
graphlayer/graphql/schema.py
graphlayer-0.2.8.dist-info/LICENSE
graphlayer-0.2.8.dist-info/METADATA
graphlayer-0.2.8.dist-info/WHEEL
graphlayer-0.2.8.dist-info/top_level.txt
graphlayer-0.2.8.dist-info/RECORD
