Metadata-Version: 2.1
Name: graphlayer
Version: 0.2.8
Summary: High-performance library for implementing GraphQL APIs
Home-page: http://github.com/mwilliamson/python-graphlayer
Author: Michael Williamson
Author-email: mike@zwobble.org
License: UNKNOWN
Keywords: graphql graph join
Platform: UNKNOWN
Classifier: Development Status :: 4 - Beta
Classifier: Intended Audience :: Developers
Classifier: Programming Language :: Python
Classifier: Programming Language :: Python :: 3
Classifier: Programming Language :: Python :: 3.6
Provides-Extra: graphql
Requires-Dist: graphql-core-next (==1.1.1) ; extra == 'graphql'
